pubmed_meta_analyzer/__init__.py
pubmed_meta_analyzer/extract_metadata.py
pubmed_meta_analyzer/find_articles.py
pubmed_meta_analyzer/merge_metadata.py
pubmed_meta_analyzer-0.1.dist-info/METADATA
pubmed_meta_analyzer-0.1.dist-info/WHEEL
pubmed_meta_analyzer-0.1.dist-info/entry_points.txt
pubmed_meta_analyzer-0.1.dist-info/top_level.txt
pubmed_meta_analyzer-0.1.dist-info/RECORD
