Metadata-Version: 2.2
Name: pubmed_meta_analyzer
Version: 0.1
Summary: A Python package to generate literature search report.
Home-page: https://github.com/nbahador/pubmed_meta_analyzer
Author: Nooshin Bahador
Author-email: nooshin.bah@gmail.com
Classifier: Programming Language :: Python :: 3
Classifier: License :: OSI Approved :: MIT License
Classifier: Operating System :: OS Independent
Requires-Python: >=3.6
Requires-Dist: pandas
Requires-Dist: openpyxl
Requires-Dist: biopython
Dynamic: author
Dynamic: author-email
Dynamic: classifier
Dynamic: description
Dynamic: description-content-type
Dynamic: home-page
Dynamic: requires-dist
Dynamic: requires-python
Dynamic: summary
